{"type": "FeatureCollection", "features": [{"type": "Feature", "geometry": {"type": "Point", "coordinates": [139.69915697046446, 35.69284048722504, -22.4]}, "properties": {"id": "c1f73ecc869f418aba084af82e0f9e4a", "category": "F012", "floor_id": "f419ea9bac8646fdbc3fda17086c2d3b", "name": null, "source": "1", "__floor": "B3", "__z_abs": -22.4}}, {"type": "Feature", "geometry": {"type": "Point", "coordinates": [139.69921418698019, 35.69273503238416, -22.4]}, "properties": {"id": "88fdcb6823d049fcaa7ed5bd9b0cc784", "category": "F013", "floor_id": "f419ea9bac8646fdbc3fda17086c2d3b", "name": null, "source": "1", "__floor": "B3", "__z_abs": -22.4}}, {"type": "Feature", "geometry": {"type": "Point", "coordinates": [139.69917173160297, 35.69291680820373, -22.4]}, "properties": {"id": "144f4a6e90464180bafc9fda66a17438", "category": "F013", "floor_id": "f419ea9bac8646fdbc3fda17086c2d3b", "name": null, "source": "1", "__floor": "B3", "__z_abs": -22.4}}, {"type": "Feature", "geometry": {"type": "Point", "coordinates": [139.69902381748074, 35.69356486887725, -22.4]}, "properties": {"id": "aa5c3c60a971437db4f320be8ee3b496", "category": "F013", "floor_id": "34aabec4cbd742abb2a0c2440b9dc4dd", "name": null, "source": "1", "__floor": "B3", "__z_abs": -22.4}}, {"type": "Feature", "geometry": {"type": "Point", "coordinates": [139.69906635378027, 35.69388622009109, -22.4]}, "properties": {"id": "208f6ffd0f3e4949afb83cb2506e4839", "category": "F013", "floor_id": "34aabec4cbd742abb2a0c2440b9dc4dd", "name": null, "source": "1", "__floor": "B3", "__z_abs": -22.4}}, {"type": "Feature", "geometry": {"type": "Point", "coordinates": [139.69908888967868, 35.69415766235757, -22.4]}, "properties": {"id": "c41220eb4f604c3fb9c27b7c857f36d4", "category": "F013", "floor_id": "d30ca5ad237349cdb5b228254801ff19", "name": null, "source": "1", "__floor": "B3", "__z_abs": -22.4}}, {"type": "Feature", "geometry": {"type": "Point", "coordinates": [139.6992127737663, 35.6942161661895, -22.4]}, "properties": {"id": "0a9bb0a34aa94e4ebb6938bb5f0a07c7", "category": "F013", "floor_id": "d30ca5ad237349cdb5b228254801ff19", "name": null, "source": "1", "__floor": "B3", "__z_abs": -22.4}}, {"type": "Feature", "geometry": {"type": "Point", "coordinates": [139.6990592563894, 35.69419222768622, -22.4]}, "properties": {"id": "5d96378002a941d28e7491c772c02832", "category": "F013", "floor_id": "d30ca5ad237349cdb5b228254801ff19", "name": null, "source": "1", "__floor": "B3", "__z_abs": -22.4}}, {"type": "Feature", "geometry": {"type": "Point", "coordinates": [139.69922670366125, 35.694179232226844, -22.4]}, "properties": {"id": "cee71c855aec4923a45f48775d4b0cf8", "category": "F013", "floor_id": "d30ca5ad237349cdb5b228254801ff19", "name": null, "source": "1", "__floor": "B3", "__z_abs": -22.4}}, {"type": "Feature", "geometry": {"type": "Point", "coordinates": [139.69905335898312, 35.694190426543265, -22.4]}, "properties": {"id": "5490b0cc8ca64d6fa5ed8c4c5baf3c6f", "category": "F108", "floor_id": null, "name": "D5", "source": "1", "__floor": "B3", "__z_abs": -22.4}}, {"type": "Feature", "geometry": {"type": "Point", "coordinates": [139.69912814113127, 35.694226110365804, -22.4]}, "properties": {"id": "793e54a3b1654061af0a0381efc90c0c", "category": "F011", "floor_id": "d30ca5ad237349cdb5b228254801ff19", "name": null, "source": "1", "__floor": "B3", "__z_abs": -22.4}}, {"type": "Feature", "geometry": {"type": "Point", "coordinates": [139.69916313525096, 35.69414520720407, -22.4]}, "properties": {"id": "cec9be9d3651488dbbe569513f2e695c", "category": "F011", "floor_id": "d30ca5ad237349cdb5b228254801ff19", "name": null, "source": "1", "__floor": "B3", "__z_abs": -22.4}}, {"type": "Feature", "geometry": {"type": "Point", "coordinates": [139.69906215996008, 35.69397588323045, -22.4]}, "properties": {"id": "73f1fda0fa0740c481285726596548e3", "category": "F011", "floor_id": "34aabec4cbd742abb2a0c2440b9dc4dd", "name": null, "source": "1", "__floor": "B3", "__z_abs": -22.4}}, {"type": "Feature", "geometry": {"type": "Point", "coordinates": [139.69902651670927, 35.69363650873151, -22.4]}, "properties": {"id": "e2bc777656b34199a36bbbaaeae91a31", "category": "F011", "floor_id": "34aabec4cbd742abb2a0c2440b9dc4dd", "name": null, "source": "1", "__floor": "B3", "__z_abs": -22.4}}, {"type": "Feature", "geometry": {"type": "Point", "coordinates": [139.6990576589232, 35.693587594962864, -22.4]}, "properties": {"id": "e5802469d0f8459188da65aa02717381", "category": "F011", "floor_id": "34aabec4cbd742abb2a0c2440b9dc4dd", "name": null, "source": "1", "__floor": "B3", "__z_abs": -22.4}}, {"type": "Feature", "geometry": {"type": "Point", "coordinates": [139.6991527275575, 35.69288800396297, -22.4]}, "properties": {"id": "5c01f7feae6142638695e10be0176e93", "category": "F011", "floor_id": "f419ea9bac8646fdbc3fda17086c2d3b", "name": null, "source": "1", "__floor": "B3", "__z_abs": -22.4}}]}